nhc/__init__.py
nhc/action.py
nhc/connection.py
nhc/const.py
nhc/controller.py
nhc/cover.py
nhc/energy.py
nhc/errors.py
nhc/events.py
nhc/fan.py
nhc/light.py
nhc/scene.py
nhc/thermostat.py
nhc-0.7.0.dist-info/licenses/LICENSE
nhc-0.7.0.dist-info/METADATA
nhc-0.7.0.dist-info/WHEEL
nhc-0.7.0.dist-info/top_level.txt
nhc-0.7.0.dist-info/RECORD
